memory_magics/__init__.py
memory_magics/_version.py
memory_magics/memory_magics.py
memory_magics/memory_tracer/__init__.py
memory_magics/memory_tracer/_memory_tracer.py
memory_magics/memory_tracer/context_memory_tracer.py
memory_magics/utils.py
ipython_memory_magics-0.3.7.dist-info/LICENSE
ipython_memory_magics-0.3.7.dist-info/WHEEL
ipython_memory_magics-0.3.7.dist-info/METADATA
ipython_memory_magics-0.3.7.dist-info/RECORD
