Metadata-Version: 2.1
Name: ipython-memory-magics
Version: 0.3.7
Summary: IPython magic commands for tracking memory usage
Home-page: https://github.com/rusmux/ipython-memory-magics
License: MIT
Keywords: memory,profiler,jupyter,magic
Author: Ruslan Mukhametshin
Author-email: rusmux21@gmail.com
Requires-Python: >=3.8,<4.0
Classifier: License :: OSI Approved :: MIT License
Classifier: Programming Language :: Python :: 3
Classifier: Programming Language :: Python :: 3.8
Classifier: Programming Language :: Python :: 3.9
Classifier: Programming Language :: Python :: 3.10
Requires-Dist: ipython (>=8.5.0,<9.0.0)
Requires-Dist: psutil (>=5.9.3,<6.0.0)
Project-URL: Repository, https://github.com/rusmux/ipython-memory-magics
